machine_learning_toolkit/__init__.py
machine_learning_toolkit/evaluator.py
machine_learning_toolkit-0.1.1.dist-info/METADATA
machine_learning_toolkit-0.1.1.dist-info/WHEEL
machine_learning_toolkit-0.1.1.dist-info/top_level.txt
machine_learning_toolkit-0.1.1.dist-info/RECORD
