Metadata-Version: 2.4
Name: machine-learning-toolkit
Version: 0.1.1
Summary: Utility for evaluating ML models with scikit-learn
Author: Your Name
Author-email: your.email@example.com
Classifier: Programming Language :: Python :: 3
Classifier: Intended Audience :: Developers
Classifier: License :: OSI Approved :: MIT License
Requires-Python: >=3.7
Requires-Dist: scikit-learn>=1.0.0
Requires-Dist: matplotlib>=3.0.0
Dynamic: author
Dynamic: author-email
Dynamic: classifier
Dynamic: requires-dist
Dynamic: requires-python
Dynamic: summary
